{"success":true,"data":{"id":"green_ecological_redline","name":"生态保护红线面积","category":"绿色","subcategory":"生态底线","unit":"km²","direction":"positive","thresholdType":"min","target":498,"warning":496,"description":"反映生态保护红线稳定性，原则上不得减少。","policyTags":["生态保护红线","国土空间规划"],"values":{"2019":505.7,"2020":505.74,"2021":501.2,"2022":496.64,"2023":497.1,"2024":498},"year":2024,"value":498,"score":100,"status":"normal","statusText":"正常","trend":{"direction":"worsening","text":"较2019年恶化1.5%","delta":-7.7,"rate":-1.5},"series":[{"year":2019,"value":505.7,"score":100,"status":"normal"},{"year":2020,"value":505.74,"score":100,"status":"normal"},{"year":2021,"value":501.2,"score":100,"status":"normal"},{"year":2022,"value":496.64,"score":81,"status":"attention"},{"year":2023,"value":497.1,"score":86,"status":"attention"},{"year":2024,"value":498,"score":100,"status":"normal"}]}}